ww3py/__init__.py
ww3py/exec/__init__.py
ww3py/exec/exe_ww3.py
ww3py/exec/pos_ww3.py
ww3py/exec/pre_ww3.py
ww3py/exec/utils.py
ww3py/plot/__init__.py
ww3py/plot/dir_dist.py
ww3py/plot/init_custom.py
ww3py/plot/misc.py
ww3py/plot/series.py
ww3py/plot/skill_1d_series.py
ww3py/plot/skill_2d_series.py
ww3py/plot/soft_topo_cmap.py
ww3py/plot/spectra_1d.py
ww3py/plot/spectra_2d.py
ww3py/plot/src_terms.py
ww3py/plot/utils.py
ww3py/util/__init__.py
ww3py/util/customize.py
ww3py/util/data.py
ww3py/util/files.py
ww3py/util/misce.py
ww3py-0.0.3.dist-info/METADATA
ww3py-0.0.3.dist-info/WHEEL
ww3py-0.0.3.dist-info/top_level.txt
ww3py-0.0.3.dist-info/RECORD
