Metadata-Version: 2.1
Name: ww3py
Version: 0.0.3
Summary: A handle python package to WWIII simulations
Home-page: UNKNOWN
Author: Franklin Ayala
Author-email: <ffayalac@unal.edu.co>
License: UNKNOWN
Keywords: python,first package
Platform: UNKNOWN
Classifier: Development Status :: 3 - Alpha
Classifier: Intended Audience :: Education
Classifier: Programming Language :: Python :: 2
Classifier: Programming Language :: Python :: 3
Classifier: Operating System :: MacOS :: MacOS X
Classifier: Operating System :: Microsoft :: Windows
